etherpad_lite/__init__.py
etherpad_lite/__main__.py
etherpad_lite-0.5.dist-info/DESCRIPTION.rst
etherpad_lite-0.5.dist-info/METADATA
etherpad_lite-0.5.dist-info/RECORD
etherpad_lite-0.5.dist-info/WHEEL
etherpad_lite-0.5.dist-info/metadata.json
etherpad_lite-0.5.dist-info/top_level.txt
