Metadata-Version: 2.0
Name: etherpad-lite
Version: 0.5
Summary: Python interface for Etherpad-Lite's HTTP API
Home-page: http://changaco.net/gitweb/?p=python-etherpad_lite.git
Author: Changaco
Author-email: changaco ατ changaco δοτ net
License: CC0
Platform: UNKNOWN
